<?xml version="1.0" encoding="UTF-8"?>
<mappings xmlns="http://dozer.sourceforge.net"
          xmlns:xsi="http://www.w3.org/2001/XMLSchema-instance"
          xsi:schemaLocation="http://dozer.sourceforge.net https://dozer.sourceforge.net/schema/beanmapping.xsd">
    <mapping>
        <class-a>ir.publications.task.model.CourseRegistration</class-a>
        <class-b>ir.publications.task.web.viewModel.CourseRegistrationViewModel</class-b>
        <field type="one-way">
            <a>year</a>
            <b>year</b>
            <a-hint>java.lang.Long</a-hint>
            <b-hint>java.lang.Long</b-hint>
        </field>
        <field>
            <a>course.id</a>
            <b>courseId</b>
            <a-hint>java.lang.Long</a-hint>
            <b-hint>java.lang.Long</b-hint>
        </field>
        <field type="one-way">
            <a>course.title</a>
            <b>courseTitle</b>
            <a-hint>java.lang.String</a-hint>
            <b-hint>java.lang.String</b-hint>
        </field>
        <field>
            <a>semester.id</a>
            <b>semesterId</b>
            <a-hint>java.lang.Long</a-hint>
            <b-hint>java.lang.Long</b-hint>
        </field>
        <field type="one-way">
            <a>semester.name</a>
            <b>semesterName</b>
            <a-hint>java.lang.String</a-hint>
            <b-hint>java.lang.String</b-hint>
        </field>
        <field>
            <a>classRoom.id</a>
            <b>classRoomId</b>
            <a-hint>java.lang.Long</a-hint>
            <b-hint>java.lang.Long</b-hint>
        </field>
    </mapping>
</mappings>